sf_config_builder-0.1.5.dist-info/licenses/LICENSE
sfconfig/__init__.py
sfconfig/config.py
sfconfig/diff.py
sfconfig/exceptions.py
sfconfig/paths.py
sfconfig/java/ConfigBuilder.jar
sf_config_builder-0.1.5.dist-info/METADATA
sf_config_builder-0.1.5.dist-info/WHEEL
sf_config_builder-0.1.5.dist-info/top_level.txt
sf_config_builder-0.1.5.dist-info/RECORD
