Metadata-Version: 2.4
Name: sf-config-builder
Version: 0.1.5
Summary: Manage Screaming Frog configs programmatically
Author: Antonio
License: MIT
Project-URL: Homepage, https://github.com/Amaculus/sf-config-builder
Project-URL: Documentation, https://github.com/Amaculus/sf-config-builder#readme
Project-URL: Repository, https://github.com/Amaculus/sf-config-builder
Project-URL: Issues, https://github.com/Amaculus/sf-config-builder/issues
Keywords: seo,screaming-frog,crawling,automation,config
Classifier: Development Status :: 4 - Beta
Classifier: Intended Audience :: Developers
Classifier: License :: OSI Approved :: MIT License
Classifier: Operating System :: OS Independent
Classifier: Programming Language :: Python :: 3
Classifier: Programming Language :: Python :: 3.8
Classifier: Programming Language :: Python :: 3.9
Classifier: Programming Language :: Python :: 3.10
Classifier: Programming Language :: Python :: 3.11
Classifier: Programming Language :: Python :: 3.12
Classifier: Topic :: Internet :: WWW/HTTP :: Indexing/Search
Classifier: Topic :: Software Development :: Libraries :: Python Modules
Requires-Python: >=3.8
License-File: LICENSE
Provides-Extra: dev
Requires-Dist: pytest>=7.0; extra == "dev"
Requires-Dist: pytest-cov>=4.0; extra == "dev"
Dynamic: license-file
